{
  "navbar.about.us": "Mer Masin",
  "navbar.home": "Գլխավոր",
  "help.tel.problem": "Ասա մեզ քո խնդրի մասին.",
  "help.text": "Փորձեք աջակցել ձեր բացատրությանը սքրինշոթով, դրանով մենք կարող ենք ավելի արագ լուծել ձեր խնդիրը:",
  "help.headline": "Վերնագիր",
  "help.problem": "Մուտքագրեք ձեր խնդիրը այստեղ",
  "help.button": "Ուղարկել",
  "help.headline.required": "Վերնագիրը պարտադիր է",
  "help.problem.required": "Խնդիրը պարտադիր է",
  "about.us.page.title": "Ո՞վ ենք մենք",
  "about.us.page.desc": "Lorem ipsum dolor sit amet consectetur. Non vel nisl iaculis faucibus ornare vitae. Lectus quam faucibus ultrices pellentesque vitae sem vestibulum potenti id. Enim tellus sagittis diam nisl mattis. Lorem ipsum dolor sit amet consectetur. Non vel nisl iaculis faucibus ornare vitae. Lectus quam faucibus ultrices pellentesque vitae sem vestibulum potenti id. Enim tellus sagittis diam nisl mattis."
}
